{
  "categories": [
    {
      "supercategory": "crab",
      "id": 1,
      "name": "crab",
      "keypoints": [
        "Left-Eye",
        "Right-Eye",
        "Left-Sharp",
        "Right-Sharp"
      ],
      "skeleton": [
        [
          0,
          2
        ],
        [
          1,
          3
        ]
      ]
    }
  ],
  "images": [
    {
      "file_name": "2.webp",
      "height": 343,
      "width": 500,
      "id": 0
    },
    {
      "file_name": "3.webp",
      "height": 270,
      "width": 400,
      "id": 1
    },
    {
      "file_name": "5.webp",
      "height": 427,
      "width": 641,
      "id": 2
    },
    {
      "file_name": "4.webp",
      "height": 500,
      "width": 667,
      "id": 3
    },
    {
      "file_name": "1.webp",
      "height": 666,
      "width": 500,
      "id": 4
    }
  ],
  "annotations": [
    {
      "category_id": 1,
      "segmentation": [],
      "area": 100,
      "iscrowd": 0,
      "image_id": 0,
      "id": 0,
      "bbox": [
        10,
        2,
        479,
        334
      ],
      "num_keypoints": 4,
      "keypoints": [
        218,
        112,
        2,
        283,
        111,
        2,
        102,
        188,
        2,
        393,
        188,
        2
      ]
    },
    {
      "category_id": 1,
      "segmentation": [],
      "area": 100,
      "iscrowd": 0,
      "image_id": 1,
      "id": 1,
      "bbox": [
        2,
        13,
        390,
        249
      ],
      "num_keypoints": 4,
      "keypoints": [
        162,
        91,
        2,
        228,
        92,
        2,
        75,
        154,
        2,
        321,
        155,
        2
      ]
    },
    {
      "category_id": 1,
      "segmentation": [],
      "area": 100,
      "iscrowd": 0,
      "image_id": 2,
      "id": 2,
      "bbox": [
        2,
        125,
        245,
        297
      ],
      "num_keypoints": 3,
      "keypoints": [
        184,
        180,
        2,
        228,
        239,
        2,
        25,
        140,
        2,
        0,
        0,
        0
      ]
    },
    {
      "category_id": 1,
      "segmentation": [],
      "area": 100,
      "iscrowd": 0,
      "image_id": 2,
      "id": 3,
      "bbox": [
        204,
        54,
        239,
        370
      ],
      "num_keypoints": 4,
      "keypoints": [
        383,
        148,
        2,
        414,
        219,
        2,
        233,
        108,
        2,
        357,
        393,
        2
      ]
    },
    {
      "category_id": 1,
      "segmentation": [],
      "area": 100,
      "iscrowd": 0,
      "image_id": 2,
      "id": 4,
      "bbox": [
        352,
        19,
        273,
        307
      ],
      "num_keypoints": 4,
      "keypoints": [
        518,
        63,
        2,
        562,
        129,
        2,
        373,
        41,
        2,
        553,
        296,
        2
      ]
    },
    {
      "category_id": 1,
      "segmentation": [],
      "area": 100,
      "iscrowd": 0,
      "image_id": 3,
      "id": 5,
      "bbox": [
        1,
        28,
        618,
        468
      ],
      "num_keypoints": 4,
      "keypoints": [
        316,
        51,
        2,
        435,
        63,
        2,
        107,
        165,
        2,
        607,
        225,
        2
      ]
    },
    {
      "category_id": 1,
      "segmentation": [
        [
          80.0,
          203.0
        ],
        [
          125.88,
          151.24
        ],
        [
          161.18,
          135.94
        ],
        [
          203.53,
          118.29
        ],
        [
          261.18,
          127.71
        ],
        [
          311.76,
          153.59
        ],
        [
          334.12,
          180.65
        ],
        [
          370.59,
          187.71
        ],
        [
          328.24,
          197.12
        ],
        [
          283.53,
          227.71
        ],
        [
          274.12,
          250.06
        ],
        [
          256.47,
          272.41
        ],
        [
          210.59,
          281.82
        ],
        [
          163.53,
          288.88
        ],
        [
          138.82,
          263.0
        ],
        [
          109.41,
          245.35
        ],
        [
          43.53,
          238.29
        ]
      ],
      "area": 100,
      "iscrowd": 0,
      "image_id": 4,
      "id": 6,
      "bbox": [
        11,
        112,
        377,
        220
      ],
      "num_keypoints": 4,
      "keypoints": [
        176,
        123,
        2,
        224,
        117,
        2,
        55,
        236,
        2,
        353,
        186,
        2
      ]
    },
    {
      "category_id": 1,
      "segmentation": [
        [
          75.29,
          445.35
        ],
        [
          129.41,
          428.88
        ],
        [
          152.94,
          394.76
        ],
        [
          162.35,
          371.24
        ],
        [
          176.47,
          341.82
        ],
        [
          183.53,
          330.06
        ],
        [
          243.53,
          317.12
        ],
        [
          284.71,
          299.47
        ],
        [
          328.24,
          303.0
        ],
        [
          362.35,
          327.71
        ],
        [
          401.18,
          337.12
        ],
        [
          447.06,
          330.06
        ],
        [
          418.82,
          358.29
        ],
        [
          401.18,
          400.65
        ],
        [
          387.06,
          433.59
        ],
        [
          356.47,
          467.71
        ],
        [
          323.53,
          492.41
        ],
        [
          265.88,
          519.47
        ],
        [
          211.76,
          520.65
        ],
        [
          160.0,
          491.24
        ],
        [
          109.41,
          461.82
        ]
      ],
      "area": 100,
      "iscrowd": 0,
      "image_id": 4,
      "id": 7,
      "bbox": [
        6,
        283,
        478,
        279
      ],
      "num_keypoints": 4,
      "keypoints": [
        383,
        444,
        2,
        298,
        511,
        2,
        439,
        330,
        2,
        78,
        457,
        2
      ]
    }
  ]
}