{
  "version": "5.1.1",
  "flags": {},
  "shapes": [
    {
      "label": "sjb_rect",
      "points": [
        [
          754.0,
          80.0
        ],
        [
          2958.0,
          1320.0
        ]
      ],
      "group_id": null,
      "shape_type": "rectangle",
      "flags": {}
    },
    {
      "label": "sjb_rect",
      "points": [
        [
          3310.0,
          1252.0
        ],
        [
          4590.0,
          3428.0
        ]
      ],
      "group_id": null,
      "shape_type": "rectangle",
      "flags": {}
    },
    {
      "label": "sjb_rect",
      "points": [
        [
          682.0,
          1784.0
        ],
        [
          2954.0,
          3124.0
        ]
      ],
      "group_id": null,
      "shape_type": "rectangle",
      "flags": {}
    },
    {
      "label": "angle_30",
      "points": [
        [
          818.0,
          1212.0
        ]
      ],
      "group_id": null,
      "shape_type": "point",
      "flags": {}
    },
    {
      "label": "angle_30",
      "points": [
        [
          718.0,
          3068.0
        ]
      ],
      "group_id": null,
      "shape_type": "point",
      "flags": {}
    },
    {
      "label": "angle_30",
      "points": [
        [
          3414.0,
          3368.0
        ]
      ],
      "group_id": null,
      "shape_type": "point",
      "flags": {}
    },
    {
      "label": "angle_60",
      "points": [
        [
          2914.0,
          116.0
        ]
      ],
      "group_id": null,
      "shape_type": "point",
      "flags": {}
    },
    {
      "label": "angle_60",
      "points": [
        [
          2878.0,
          1832.0
        ]
      ],
      "group_id": null,
      "shape_type": "point",
      "flags": {}
    },
    {
      "label": "angle_60",
      "points": [
        [
          4558.0,
          1336.0
        ]
      ],
      "group_id": null,
      "shape_type": "point",
      "flags": {}
    },
    {
      "label": "angle_90",
      "points": [
        [
          2902.0,
          1264.0
        ]
      ],
      "group_id": null,
      "shape_type": "point",
      "flags": {}
    },
    {
      "label": "angle_90",
      "points": [
        [
          2898.0,
          3068.0
        ]
      ],
      "group_id": null,
      "shape_type": "point",
      "flags": {}
    },
    {
      "label": "angle_90",
      "points": [
        [
          3370.0,
          1320.0
        ]
      ],
      "group_id": null,
      "shape_type": "point",
      "flags": {}
    },
    {
      "label": "sjb_poly",
      "points": [
        [
          794.0,
          1216.0
        ],
        [
          2922.0,
          96.0
        ],
        [
          2910.0,
          1280.0
        ]
      ],
      "group_id": null,
      "shape_type": "polygon",
      "flags": {}
    },
    {
      "label": "sjb_poly",
      "points": [
        [
          722.0,
          3076.0
        ],
        [
          2890.0,
          1804.0
        ],
        [
          2910.0,
          3080.0
        ]
      ],
      "group_id": null,
      "shape_type": "polygon",
      "flags": {}
    },
    {
      "label": "sjb_poly",
      "points": [
        [
          3366.0,
          1312.0
        ],
        [
          3409.0000000000005,
          3416.0000000000005
        ],
        [
          4574.0,
          1312.0
        ]
      ],
      "group_id": null,
      "shape_type": "polygon",
      "flags": {}
    }
  ],
  "imagePath": "DSC_0372.jpg",
  "imageData": null,
  "imageHeight": 3712,
  "imageWidth": 5568
}